tpcp/__init__.py
tpcp/_algorithm.py
tpcp/_algorithm_utils.py
tpcp/_base.py
tpcp/_dataset.py
tpcp/_hash.py
tpcp/_optimize.py
tpcp/_parameters.py
tpcp/_pipeline.py
tpcp/_utils/__init__.py
tpcp/_utils/_general.py
tpcp/_utils/_score.py
tpcp/caching.py
tpcp/exceptions.py
tpcp/misc/__init__.py
tpcp/misc/_class_utils.py
tpcp/misc/_typed_iterator.py
tpcp/optimize/__init__.py
tpcp/optimize/_optimize.py
tpcp/optimize/optuna.py
tpcp/parallel.py
tpcp/testing/__init__.py
tpcp/testing/_algorithm_test_mixin.py
tpcp/testing/_regression_utils.py
tpcp/types.py
tpcp/validate/__init__.py
tpcp/validate/_cross_val_helper.py
tpcp/validate/_scorer.py
tpcp/validate/_validate.py
tpcp-2.1.0.dist-info/LICENSE
tpcp-2.1.0.dist-info/METADATA
tpcp-2.1.0.dist-info/WHEEL
tpcp-2.1.0.dist-info/entry_points.txt
tpcp-2.1.0.dist-info/RECORD
