Metadata-Version: 2.3
Name: tpcp
Version: 2.1.0
Summary: Pipeline and Dataset helpers for complex algorithm evaluation.
Author: Arne Küderle
Author-email: arne.kuederle@fau.de
Requires-Python: >=3.9,<4.0
Classifier: Programming Language :: Python :: 3
Classifier: Programming Language :: Python :: 3.9
Classifier: Programming Language :: Python :: 3.10
Classifier: Programming Language :: Python :: 3.11
Classifier: Programming Language :: Python :: 3.12
Classifier: Programming Language :: Python :: 3.13
Provides-Extra: attrs
Provides-Extra: optuna
Provides-Extra: x-tensorflow
Provides-Extra: x-torch-cpu
Requires-Dist: attrs (>=22.1.0) ; extra == "attrs"
Requires-Dist: joblib (>=1.3)
Requires-Dist: numpy (>=1.0)
Requires-Dist: optuna (>=2.10) ; extra == "optuna"
Requires-Dist: pandas (>=1.3)
Requires-Dist: scikit-learn (>=1.2.0)
Requires-Dist: tensorflow-cpu (>=2.16.0) ; extra == "x-tensorflow"
Requires-Dist: torch (>=1.6.0) ; extra == "x-torch-cpu"
Requires-Dist: tqdm (>=4.62.3)
Requires-Dist: typing-extensions (>=4.1.1)
Project-URL: Homepage, https://github.com/mad-lab-fau/tpcp
Project-URL: Repository, https://github.com/mad-lab-fau/tpcp
